ttkode/__init__.py
ttkode/__main__.py
ttkode/helper.py
ttkode/plugin.py
ttkode/proxy.py
ttkode/app/__init__.py
ttkode/app/about.py
ttkode/app/activitybar.py
ttkode/app/cfg.py
ttkode/app/options.py
ttkode/app/state.py
ttkode/app/ttkode.py
ttkode/plugins/_010_findplugin.py
ttkode/plugins/_020_debugplugin.py
ttkode/plugins/_030_pytestplugin.py
ttkode/plugins/testplugin.py
ttkode/plugins/testplugin1.py
ttkode/plugins/_010/__init__.py
ttkode/plugins/_010/findwidget.py
ttkode-0.48.1a0.dist-info/METADATA
ttkode-0.48.1a0.dist-info/WHEEL
ttkode-0.48.1a0.dist-info/entry_points.txt
ttkode-0.48.1a0.dist-info/top_level.txt
ttkode-0.48.1a0.dist-info/RECORD
