Metadata-Version: 2.4
Name: ttkode
Version: 0.48.1a0
Summary: Terminal ToolKit Studio Code editor
Author-email: Eugenio Parodi <ceccopierangiolieugenio@googlemail.com>
License: MIT
Project-URL: Homepage, https://github.com/ceccopierangiolieugenio/pyTermTk/tree/main/apps/ttkode
Project-URL: Repository, https://github.com/ceccopierangiolieugenio/pyTermTk.git
Project-URL: Issues, https://github.com/ceccopierangiolieugenio/pyTermTk/issues
Project-URL: Changelog, https://github.com/ceccopierangiolieugenio/pyTermTk/blob/main/apps/ttkode/CHANGELOG.md
Classifier: Programming Language :: Python :: 3
Classifier: License :: OSI Approved :: MIT License
Classifier: Operating System :: OS Independent
Classifier: Development Status :: 3 - Alpha
Classifier: Environment :: Console
Classifier: Intended Audience :: Developers
Classifier: Intended Audience :: Information Technology
Classifier: Topic :: Terminals
Classifier: Topic :: Software Development :: User Interfaces
Requires-Python: >=3.9
Requires-Dist: pyTermTk>=0.48.1-a0
Requires-Dist: appdirs
Requires-Dist: copykitten
Requires-Dist: pygments
